{"stats":{"minecraft:mined":{"minecraft:fire":6},"minecraft:broken":{"minecraft:netherite_leggings":1,"minecraft:netherite_helmet":1,"minecraft:netherite_boots":1,"minecraft:netherite_chestplate":1},"minecraft:used":{"minecraft:netherite_helmet":1},"minecraft:custom":{"minecraft:jump":6,"minecraft:time_since_rest":546,"minecraft:leave_game":1,"minecraft:deaths":3,"minecraft:sprint_one_cm":381,"minecraft:play_time":5877,"minecraft:damage_taken":38943,"minecraft:time_since_death":0,"minecraft:walk_one_cm":2248,"minecraft:total_world_time":5877,"minecraft:fall_one_cm":1277,"minecraft:fly_one_cm":4883}},"DataVersion":3465}